cirrus/plugins/management/__init__.py
cirrus/plugins/management/deployment.py
cirrus/plugins/management/exceptions.py
cirrus/plugins/management/commands/__init__.py
cirrus/plugins/management/commands/deployments.py
cirrus/plugins/management/commands/manage.py
cirrus/plugins/management/commands/payload.py
cirrus/plugins/management/utils/__init__.py
cirrus/plugins/management/utils/boto3.py
cirrus/plugins/management/utils/click.py
cirrus/plugins/management/utils/templating.py
cirrus_mgmt-0.1.1.dist-info/LICENSE
cirrus_mgmt-0.1.1.dist-info/METADATA
cirrus_mgmt-0.1.1.dist-info/WHEEL
cirrus_mgmt-0.1.1.dist-info/dependency_links.txt
cirrus_mgmt-0.1.1.dist-info/entry_points.txt
cirrus_mgmt-0.1.1.dist-info/top_level.txt
cirrus_mgmt-0.1.1.dist-info/RECORD
