Metadata-Version: 2.1
Name: cirrus-mgmt
Version: 0.1.1
Summary: cirrus-geo plugin providing deployment management commands
Home-page: https://github.com/cirrus-geo/cirrus-mgmt
Author: Jarrett Keifer (jkeifer), Element 84
License: Apache-2.0
Classifier: Intended Audience :: Developers
Classifier: License :: OSI Approved :: Apache Software License
Classifier: Programming Language :: Python :: 3.8
Classifier: Programming Language :: Python :: 3.9
Classifier: Programming Language :: Python :: 3.10
Classifier: Programming Language :: Python :: 3.11
License-File: LICENSE
Requires-Dist: click-option-group >=0.5.5
Requires-Dist: cirrus-geo >=0.9.0
Requires-Dist: backoff >=2.2.1
